[
    {
        "id": "3249",
        "original_text": "小玉今年9月1日把积攒的400元压岁钱存入银行，定期3年，年利率2.89%，准备到期时把利息捐给希望工程，到时她可捐款多少钱？",
        "mask_text": "小玉 今年 N0 月 N1 日 把 积攒 的 N2 元 压岁钱 存入 银行 ， 定期 N3 年 ， 年利率 N4 ， 准备 到期 时 把 利息 捐给 希望工程 ， 到 时 她 可 捐款 多少 钱 ？",
        "context": "小玉今年9月1日把积攒的400元压岁钱存入银行，定期3年，年利率2.89%，准备到期时把利息捐给希望工程，",
        "original_question": "到时她可捐款多少钱？",
        "nums": "9 1 400 3 2.89%",
        "equ_unbias": {
            "N2": "",
            "N4": "",
            "N3": "",
            "N2 + N4": "",
            "N2 - N4": "",
            "N2 * N4": "",
            "N2 / N4": "",
            "N2 + N3": "",
            "N2 - N3": "",
            "N2 * N3": "",
            "N2 / N3": "",
            "N4 - N2": "",
            "N4 / N2": "",
            "N4 + N3": "",
            "N4 - N3": "",
            "N4 * N3": "",
            "N4 / N3": "",
            "N3 - N2": "",
            "N3 / N2": "",
            "N3 - N4": "",
            "N3 / N4": "",
            "( N2 * N4 ) * N3": "到时她可捐款多少钱？",
            "( N2 + N4 ) * N3": "",
            "( N2 * N4 ) + N3": "",
            "( N2 * N4 ) - N3": "",
            "( N2 * N4 ) / N3": "",
            "( N2 - N4 ) * N3": "",
            "( N2 / N4 ) * N3": ""
        }
    },
    {
        "id": "7951",
        "original_text": "甲乙两车同时从两地相对开出，甲车每小时行32千米，乙车每小时行30千米，相遇时甲车比乙车多行16千米．求两地相距多少千米．",
        "mask_text": "甲乙 两车 同时 从 两地 相对 开出 ， 甲车 每 小时 行 N0 千米 ， 乙车 每 小时 行 N1 千米 ， 相遇 时甲车 比乙车 多行 N2 千米 ． 求 两地 相距 多少 千米 ．",
        "context": "甲乙两车同时从两地相对开出，甲车每小时行32千米，乙车每小时行30千米，相遇时甲车比乙车多行16千米．",
        "original_question": "求两地相距多少千米．",
        "nums": "32 30 16",
        "equ_unbias": {
            "N0": "",
            "N1": "",
            "N2": "",
            "N0 + N1": "",
            "N0 - N1": "",
            "N0 * N1": "",
            "N0 / N1": "",
            "N0 + N2": "",
            "N0 - N2": "",
            "N0 * N2": "",
            "N0 / N2": "",
            "N0 + N0": "",
            "N0 - N0": "",
            "N0 * N0": "",
            "N0 / N0": "",
            "N1 - N0": "",
            "N1 / N0": "",
            "N1 + N2": "",
            "N1 - N2": "",
            "N1 * N2": "",
            "N1 / N2": "",
            "N1 + N0": "",
            "N1 * N0": "",
            "N1 + N1": "",
            "N1 - N1": "",
            "N1 * N1": "",
            "N1 / N1": "",
            "N2 - N0": "",
            "N2 / N0": "",
            "N2 - N1": "",
            "N2 / N1": "",
            "N2 + N0": "",
            "N2 * N0": "",
            "N2 + N1": "",
            "N2 * N1": "",
            "N2 / ( N0 - N1 )": "",
            "( N0 + N1 ) * ( N2 / ( N0 - N1 ) )": "求两地相距多少千米．",
            "N2 + ( N0 - N1 )": "",
            "N2 / ( N0 + N1 )": "",
            "N2 / ( N0 * N1 )": "",
            "N2 / ( N0 / N1 )": "",
            "N2 - ( N0 - N1 )": "",
            "N2 * ( N0 - N1 )": ""
        }
    },
    {
        "id": "10907",
        "original_text": "姐姐和妹妹都从家到学校上学，姐姐每分钟走55米，妹妹每分钟走40米，姐姐让妹妹先走3分钟，然后姐姐才出发追赶妹妹，经过多少分钟姐姐可以追上妹妹？",
        "mask_text": "姐姐 和 妹妹 都 从家 到 学校 上学 ， 姐姐 每分钟 走 N0 米 ， 妹妹 每分钟 走 N1 米 ， 姐姐 让 妹妹 先走 N2 分钟 ， 然后 姐姐 才 出发 追赶 妹妹 ， 经过 多少 分钟 姐姐 可以 追 上 妹妹 ？",
        "context": "姐姐和妹妹都从家到学校上学，姐姐每分钟走55米，妹妹每分钟走40米，姐姐让妹妹先走3分钟，然后姐姐才出发追赶妹妹，",
        "original_question": "经过多少分钟姐姐可以追上妹妹？",
        "nums": "55 40 3",
        "equ_unbias": {
            "N1": "",
            "N2": "",
            "N0": "",
            "N1 + N2": "",
            "N1 - N2": "",
            "N1 * N2": "",
            "N1 / N2": "",
            "N1 + N0": "",
            "N1 - N0": "",
            "N1 * N0": "",
            "N1 / N0": "",
            "N1 + N1": "",
            "N1 - N1": "",
            "N1 * N1": "",
            "N1 / N1": "",
            "N2 - N1": "",
            "N2 / N1": "",
            "N2 + N0": "",
            "N2 - N0": "",
            "N2 * N0": "",
            "N2 / N0": "",
            "N2 + N1": "",
            "N2 * N1": "",
            "N0 - N1": "",
            "N0 / N1": "",
            "N0 - N2": "",
            "N0 / N2": "",
            "N0 + N1": "",
            "N0 * N1": "",
            "( N1 * N2 ) / ( N0 - N1 )": "经过多少分钟姐姐可以追上妹妹？"
        }
    },
    {
        "id": "1470",
        "original_text": "运动会上，六年级的总分是64分，比五年级多(1/7)，五年级的总分=？",
        "mask_text": "运动会 上 ， 六年级 的 总分 是 N0 分 ， 比 五年级 多 N1 ， 五年级 的 总分 = ？",
        "context": "运动会上，六年级的总分是64分，比五年级多(1/7)，",
        "original_question": "五年级的总分=？",
        "nums": "64 (1/7)",
        "equ_unbias": {
            "N0": "",
            "1": "",
            "N1": "",
            "N0 + 1": "",
            "N0 - 1": "",
            "N0 * 1": "",
            "N0 / 1": "",
            "N0 + N1": "",
            "N0 - N1": "",
            "N0 * N1": "",
            "N0 / N1": "",
            "1 - N0": "",
            "1 / N0": "",
            "1 + N1": "",
            "1 - N1": "",
            "1 * N1": "",
            "1 / N1": "",
            "N1 - N0": "",
            "N1 / N0": "",
            "N1 - 1": "",
            "N1 / 1": "",
            "N0 / ( 1 + N1 )": "五年级的总分=？",
            "N0 + ( 1 + N1 )": "",
            "N0 / ( 1 - N1 )": "",
            "N0 / ( 1 * N1 )": "",
            "N0 / ( 1 / N1 )": "",
            "N0 - ( 1 + N1 )": "",
            "N0 * ( 1 + N1 )": ""
        }
    },
    {
        "id": "6478",
        "original_text": "小客车的辆数是大客车的160%，小客车的辆数比大客车多多少%．",
        "mask_text": "小客车 的 辆数 是 大客车 的 N0 ， 小客车 的 辆数 比 大客车 多 多少 % ．",
        "context": "小客车的辆数是大客车的160%，",
        "original_question": "小客车的辆数比大客车多多少%．",
        "nums": "160%",
        "equ_unbias": {
            "N0": "",
            "1": "",
            "N0 + 1": "",
            "N0 - 1": "小客车的辆数比大客车多多少%．",
            "N0 * 1": "",
            "N0 / 1": "",
            "1 - N0": "",
            "1 / N0": ""
        }
    },
    {
        "id": "7454",
        "original_text": "在航模比赛现场，六年级有观众245名，比五年级的多(1/4)，五年级有观众多少名？",
        "mask_text": "在 航模 比赛 现场 ， 六年级 有 观众 N0 名 ， 比 五年级 的 多 N1 ， 五年级 有 观众 多少 名 ？",
        "context": "在航模比赛现场，六年级有观众245名，比五年级的多(1/4)，",
        "original_question": "五年级有观众多少名？",
        "nums": "245 (1/4)",
        "equ_unbias": {
            "N0": "",
            "1": "",
            "N1": "",
            "N0 + 1": "",
            "N0 - 1": "",
            "N0 * 1": "",
            "N0 / 1": "",
            "N0 + N1": "",
            "N0 - N1": "",
            "N0 * N1": "",
            "N0 / N1": "",
            "1 - N0": "",
            "1 / N0": "",
            "1 + N1": "",
            "1 - N1": "",
            "1 * N1": "",
            "1 / N1": "",
            "N1 - N0": "",
            "N1 / N0": "",
            "N1 - 1": "",
            "N1 / 1": "",
            "N0 / ( 1 + N1 )": "五年级有观众多少名？",
            "N0 + ( 1 + N1 )": "",
            "N0 / ( 1 - N1 )": "",
            "N0 / ( 1 * N1 )": "",
            "N0 / ( 1 / N1 )": "",
            "N0 - ( 1 + N1 )": "",
            "N0 * ( 1 + N1 )": ""
        }
    },
    {
        "id": "8153",
        "original_text": "全世界哺乳类动物约有4000种，其中我国约有500种，我国哺乳类动物占全世界的百分之几？",
        "mask_text": "全世界 哺乳类 动物 约 有 N0 种 ， 其中 我国 约 有 N1 种 ， 我国 哺乳类 动物 占 全世界 的 百分之几 ？",
        "context": "全世界哺乳类动物约有4000种，其中我国约有500种，",
        "original_question": "我国哺乳类动物占全世界的百分之几？",
        "nums": "4000 500",
        "equ_unbias": {
            "N1": "",
            "N0": "",
            "N1 + N0": "",
            "N1 - N0": "",
            "N1 * N0": "",
            "N1 / N0": "我国哺乳类动物占全世界的百分之几？",
            "N0 - N1": "",
            "N0 / N1": ""
        }
    },
    {
        "id": "8650",
        "original_text": "学校美术作品展中，有50幅水彩画，60幅蜡笔画，蜡笔画比水彩画多百分之几？",
        "mask_text": "学校 美术 作品展 中 ， 有 N0 幅 水彩画 ， N1 幅 蜡笔画 ， 蜡笔画 比 水彩画 多 百分之几 ？",
        "context": "学校美术作品展中，有50幅水彩画，60幅蜡笔画，",
        "original_question": "蜡笔画比水彩画多百分之几？",
        "nums": "50 60",
        "equ_unbias": {
            "N1": "",
            "N0": "",
            "N1 + N0": "",
            "N1 - N0": "",
            "N1 * N0": "",
            "N1 / N0": "",
            "N0 - N1": "",
            "N0 / N1": "",
            "N0 + N0": "",
            "N0 - N0": "",
            "N0 * N0": "",
            "N0 / N0": "",
            "( N1 - N0 ) / N0": "蜡笔画比水彩画多百分之几？",
            "( N1 + N0 ) / N0": "",
            "( N1 - N0 ) + N0": "",
            "( N1 - N0 ) - N0": "",
            "( N1 - N0 ) * N0": "",
            "( N1 * N0 ) / N0": "",
            "( N1 / N0 ) / N0": ""
        }
    },
    {
        "id": "10801",
        "original_text": "修一条500米的公路，已经修了(2/5)，还剩下多少米？",
        "mask_text": "修 一条 N0 米 的 公路 ， 已经 修 了 N1 ， 还 剩下 多少 米 ？",
        "context": "修一条500米的公路，已经修了(2/5)，",
        "original_question": "还剩下多少米？",
        "nums": "500 (2/5)",
        "equ_unbias": {
            "N0": "",
            "1": "",
            "N1": "",
            "N0 + 1": "",
            "N0 - 1": "",
            "N0 * 1": "",
            "N0 / 1": "",
            "N0 + N1": "",
            "N0 - N1": "",
            "N0 * N1": "",
            "N0 / N1": "",
            "1 - N0": "",
            "1 / N0": "",
            "1 + N1": "",
            "1 - N1": "",
            "1 * N1": "",
            "1 / N1": "",
            "N1 - N0": "",
            "N1 / N0": "",
            "N1 - 1": "",
            "N1 / 1": "",
            "N0 * ( 1 - N1 )": "还剩下多少米？",
            "N0 + ( 1 - N1 )": "",
            "N0 * ( 1 + N1 )": "",
            "N0 * ( 1 * N1 )": "",
            "N0 * ( 1 / N1 )": "",
            "N0 - ( 1 - N1 )": "",
            "N0 / ( 1 - N1 )": ""
        }
    },
    {
        "id": "138",
        "original_text": "把2克盐溶解在200克的水里面，盐的质量占盐水的几分之几？",
        "mask_text": "把 N0 克盐 溶解 在 N1 克 的 水 里面 ， 盐 的 质量 占 盐水 的 几分 之 几 ？",
        "context": "把2克盐溶解在200克的水里面，",
        "original_question": "盐的质量占盐水的几分之几？",
        "nums": "2 200",
        "equ_unbias": {
            "N0": "",
            "N1": "",
            "N0 + N0": "",
            "N0 - N0": "",
            "N0 * N0": "",
            "N0 / N0": "",
            "N0 + N1": "",
            "N0 - N1": "",
            "N0 * N1": "",
            "N0 / N1": "",
            "N1 - N0": "",
            "N1 / N0": "",
            "N0 / ( N0 + N1 )": "盐的质量占盐水的几分之几？",
            "N0 + ( N0 + N1 )": "",
            "N0 / ( N0 - N1 )": "",
            "N0 / ( N0 * N1 )": "",
            "N0 / ( N0 / N1 )": "",
            "N0 - ( N0 + N1 )": "",
            "N0 * ( N0 + N1 )": ""
        }
    },
    {
        "id": "6275",
        "original_text": "熊猫的体重是432千克，大象的体重是熊猫的8.6倍，大像有多重？",
        "mask_text": "熊猫 的 体重 是 N0 千克 ， 大象 的 体重 是 熊猫 的 N1 倍 ， 大像 有 多重 ？",
        "context": "熊猫的体重是432千克，大象的体重是熊猫的8.6倍，",
        "original_question": "大像有多重？",
        "nums": "432 8.6",
        "equ_unbias": {
            "N0": "",
            "N1": "",
            "N0 + N1": "",
            "N0 - N1": "",
            "N0 * N1": "大像有多重？",
            "N0 / N1": "",
            "N1 - N0": "",
            "N1 / N0": ""
        }
    },
    {
        "id": "9321",
        "original_text": "人民路两旁从头到尾各安装了51盏灯，每相邻两盏间隔10米，这条路全长多少米．",
        "mask_text": "人民 路 两旁 从头到尾 各 安装 了 N0 盏灯 ， 每 相邻 两盏 间隔 N1 米 ， 这条 路 全长 多少 米 ．",
        "context": "人民路两旁从头到尾各安装了51盏灯，每相邻两盏间隔10米，",
        "original_question": "这条路全长多少米．",
        "nums": "51 10",
        "equ_unbias": {
            "N0": "",
            "1": "",
            "N1": "",
            "N0 + 1": "",
            "N0 - 1": "",
            "N0 * 1": "",
            "N0 / 1": "",
            "N0 + N1": "",
            "N0 - N1": "",
            "N0 * N1": "",
            "N0 / N1": "",
            "1 - N0": "",
            "1 / N0": "",
            "1 + N1": "",
            "1 - N1": "",
            "1 * N1": "",
            "1 / N1": "",
            "N1 - N0": "",
            "N1 / N0": "",
            "N1 - 1": "",
            "N1 / 1": "",
            "( N0 - 1 ) * N1": "这条路全长多少米．",
            "( N0 + 1 ) * N1": "",
            "( N0 - 1 ) + N1": "",
            "( N0 - 1 ) - N1": "",
            "( N0 - 1 ) / N1": "",
            "( N0 * 1 ) * N1": "",
            "( N0 / 1 ) * N1": ""
        }
    },
    {
        "id": "14389",
        "original_text": "一段钢材长8米，做一个零件用(3/8)米．已经做了20个这样的零件，还剩多少米？",
        "mask_text": "一段 钢材 长 N0 米 ， 做 一个 零件 用 N1 米 ． 已经 做 了 N2 个 这样 的 零件 ， 还 剩 多少 米 ？",
        "context": "一段钢材长8米，做一个零件用(3/8)米．已经做了20个这样的零件，",
        "original_question": "还剩多少米？",
        "nums": "8 (3/8) 20",
        "equ_unbias": {
            "N0": "",
            "N2": "",
            "N1": "",
            "N0 + N2": "",
            "N0 - N2": "",
            "N0 * N2": "",
            "N0 / N2": "",
            "N0 + N1": "",
            "N0 - N1": "",
            "N0 * N1": "",
            "N0 / N1": "",
            "N2 - N0": "",
            "N2 / N0": "",
            "N2 + N1": "",
            "N2 - N1": "",
            "N2 * N1": "",
            "N2 / N1": "",
            "N1 - N0": "",
            "N1 / N0": "",
            "N1 - N2": "",
            "N1 / N2": "",
            "N0 - ( N2 * N1 )": "还剩多少米？",
            "N0 + ( N2 * N1 )": "",
            "N0 - ( N2 + N1 )": "",
            "N0 - ( N2 - N1 )": "",
            "N0 - ( N2 / N1 )": "",
            "N0 * ( N2 * N1 )": "",
            "N0 / ( N2 * N1 )": ""
        }
    },
    {
        "id": "9134",
        "original_text": "刘师傅加工一批零件，如果每天加工12个，要50天完成，如果每天多加工3个，需要多少天完成？",
        "mask_text": "刘师傅 加工 一批 零件 ， 如果 每天 加工 N0 个 ， 要 N1 天 完成 ， 如果 每天 多 加工 N2 个 ， 需要 多少 天 完成 ？",
        "context": "刘师傅加工一批零件，如果每天加工12个，要50天完成，如果每天多加工3个，",
        "original_question": "需要多少天完成？",
        "nums": "12 50 3",
        "equ_unbias": {
            "N0": "",
            "N1": "",
            "N2": "",
            "N0 + N1": "",
            "N0 - N1": "",
            "N0 * N1": "",
            "N0 / N1": "",
            "N0 + N0": "",
            "N0 - N0": "",
            "N0 * N0": "",
            "N0 / N0": "",
            "N0 + N2": "",
            "N0 - N2": "",
            "N0 * N2": "",
            "N0 / N2": "",
            "N1 - N0": "",
            "N1 / N0": "",
            "N1 + N0": "",
            "N1 * N0": "",
            "N1 + N2": "",
            "N1 - N2": "",
            "N1 * N2": "",
            "N1 / N2": "",
            "N2 - N0": "",
            "N2 / N0": "",
            "N2 - N1": "",
            "N2 / N1": "",
            "( N0 * N1 ) / ( N0 + N2 )": "需要多少天完成？"
        }
    },
    {
        "id": "1118",
        "original_text": "小英说：“我做了38朵红花，18朵黄花．”小玲说：“我要将小英做的花扎成花束，每8朵扎成一束，可以扎成多少束？”请你帮小玲算一算．",
        "mask_text": "小英 说 ： “ 我 做 了 N0 朵 红花 ， N1 朵 黄花 ． ” 小玲 说 ： “ 我要 将 小英 做 的 花 扎成 花束 ， 每 N2 朵 扎成 一束 ， 可以 扎成 多少 束 ？ ” 请 你 帮小玲算 一算 ．",
        "context": "小英说：“我做了38朵红花，18朵黄花．”小玲说：“我要将小英做的花扎成花束，每8朵扎成一束，可以扎成多少束？”",
        "original_question": "请你帮小玲算一算．",
        "nums": "38 18 8",
        "equ_unbias": {
            "N0": "",
            "N1": "",
            "N2": "",
            "N0 + N1": "",
            "N0 - N1": "",
            "N0 * N1": "",
            "N0 / N1": "",
            "N0 + N2": "",
            "N0 - N2": "",
            "N0 * N2": "",
            "N0 / N2": "",
            "N1 - N0": "",
            "N1 / N0": "",
            "N1 + N2": "",
            "N1 - N2": "",
            "N1 * N2": "",
            "N1 / N2": "",
            "N2 - N0": "",
            "N2 / N0": "",
            "N2 - N1": "",
            "N2 / N1": "",
            "( N0 + N1 ) / N2": "请你帮小玲算一算．",
            "( N0 + N1 ) + N2": "",
            "( N0 + N1 ) - N2": "",
            "( N0 + N1 ) * N2": "",
            "( N0 - N1 ) / N2": "",
            "( N0 * N1 ) / N2": "",
            "( N0 / N1 ) / N2": ""
        }
    },
    {
        "id": "9258",
        "original_text": "王叔叔骑自行车的速度是每小时18千米，他从甲地到乙地需要6小时．如果改乘汽车要2小时，汽车每小时行多少千米？",
        "mask_text": "王 叔叔 骑 自行车 的 速度 是 每 小时 N0 千米 ， 他 从 甲地 到 乙地 需要 N1 小时 ． 如果 改乘 汽车 要 N2 小时 ， 汽车 每 小时 行 多少 千米 ？",
        "context": "王叔叔骑自行车的速度是每小时18千米，他从甲地到乙地需要6小时．如果改乘汽车要2小时，",
        "original_question": "汽车每小时行多少千米？",
        "nums": "18 6 2",
        "equ_unbias": {
            "N0": "",
            "N1": "",
            "N2": "",
            "N0 + N1": "",
            "N0 - N1": "",
            "N0 * N1": "",
            "N0 / N1": "",
            "N0 + N2": "",
            "N0 - N2": "",
            "N0 * N2": "",
            "N0 / N2": "",
            "N1 - N0": "",
            "N1 / N0": "",
            "N1 + N2": "",
            "N1 - N2": "",
            "N1 * N2": "",
            "N1 / N2": "",
            "N2 - N0": "",
            "N2 / N0": "",
            "N2 - N1": "",
            "N2 / N1": "",
            "( N0 * N1 ) / N2": "汽车每小时行多少千米？",
            "( N0 + N1 ) / N2": "",
            "( N0 * N1 ) + N2": "",
            "( N0 * N1 ) - N2": "",
            "( N0 * N1 ) * N2": "",
            "( N0 - N1 ) / N2": "",
            "( N0 / N1 ) / N2": ""
        }
    },
    {
        "id": "5613",
        "original_text": "小明现在的体重是36千克，比去年增加了(1/17)．去年体重多少千克？",
        "mask_text": "小明 现在 的 体重 是 N0 千克 ， 比 去年 增加 了 N1 ． 去年 体重 多少 千克 ？",
        "context": "小明现在的体重是36千克，比去年增加了(1/17)．",
        "original_question": "去年体重多少千克？",
        "nums": "36 (1/17)",
        "equ_unbias": {
            "N0": "",
            "1": "",
            "N1": "",
            "N0 + 1": "",
            "N0 - 1": "",
            "N0 * 1": "",
            "N0 / 1": "",
            "N0 + N1": "",
            "N0 - N1": "",
            "N0 * N1": "",
            "N0 / N1": "",
            "1 - N0": "",
            "1 / N0": "",
            "1 + N1": "",
            "1 - N1": "",
            "1 * N1": "",
            "1 / N1": "",
            "N1 - N0": "",
            "N1 / N0": "",
            "N1 - 1": "",
            "N1 / 1": "",
            "N0 / ( 1 + N1 )": "去年体重多少千克？",
            "N0 + ( 1 + N1 )": "",
            "N0 / ( 1 - N1 )": "",
            "N0 / ( 1 * N1 )": "",
            "N0 / ( 1 / N1 )": "",
            "N0 - ( 1 + N1 )": "",
            "N0 * ( 1 + N1 )": ""
        }
    },
    {
        "id": "5612",
        "original_text": "一块平行四边形的花圃，它的底是30m，高25m．如果每平方米草坪需要36元，那么铺满整块草坪需要多少钱？",
        "mask_text": "一块 平行四边形 的 花圃 ， 它 的 底 是 N0 m ， 高 N1 m ． 如果 每平方米 草坪 需要 N2 元 ， 那么 铺满 整块 草坪 需要 多少 钱 ？",
        "context": "一块平行四边形的花圃，它的底是30m，高25m．如果每平方米草坪需要36元，",
        "original_question": "那么铺满整块草坪需要多少钱？",
        "nums": "30 25 36",
        "equ_unbias": {
            "N0": "",
            "N1": "",
            "N2": "",
            "N0 + N1": "",
            "N0 - N1": "",
            "N0 * N1": "",
            "N0 / N1": "",
            "N0 + N2": "",
            "N0 - N2": "",
            "N0 * N2": "",
            "N0 / N2": "",
            "N1 - N0": "",
            "N1 / N0": "",
            "N1 + N2": "",
            "N1 - N2": "",
            "N1 * N2": "",
            "N1 / N2": "",
            "N2 - N0": "",
            "N2 / N0": "",
            "N2 - N1": "",
            "N2 / N1": "",
            "( N0 * N1 ) * N2": "那么铺满整块草坪需要多少钱？",
            "( N0 + N1 ) * N2": "",
            "( N0 * N1 ) + N2": "",
            "( N0 * N1 ) - N2": "",
            "( N0 * N1 ) / N2": "",
            "( N0 - N1 ) * N2": "",
            "( N0 / N1 ) * N2": ""
        }
    },
    {
        "id": "3740",
        "original_text": "某村修一条水渠，5天修了520米，照这样算，再修8天就完成了任务，这条水渠有多长？",
        "mask_text": "某村 修 一条 水渠 ， N0 天修 了 N1 米 ， 照 这样 算 ， 再修 N2 天 就 完成 了 任务 ， 这 条 水渠 有 多长 ？",
        "context": "某村修一条水渠，5天修了520米，照这样算，再修8天就完成了任务，",
        "original_question": "这条水渠有多长？",
        "nums": "5 520 8",
        "equ_unbias": {
            "N1": "",
            "N0": "",
            "N2": "",
            "N1 + N0": "",
            "N1 - N0": "",
            "N1 * N0": "",
            "N1 / N0": "",
            "N1 + N2": "",
            "N1 - N2": "",
            "N1 * N2": "",
            "N1 / N2": "",
            "N0 - N1": "",
            "N0 / N1": "",
            "N0 + N0": "",
            "N0 - N0": "",
            "N0 * N0": "",
            "N0 / N0": "",
            "N0 + N2": "",
            "N0 - N2": "",
            "N0 * N2": "",
            "N0 / N2": "",
            "N2 - N1": "",
            "N2 / N1": "",
            "N2 - N0": "",
            "N2 / N0": "",
            "( N1 / N0 ) * ( N0 + N2 )": "这条水渠有多长？"
        }
    },
    {
        "id": "8240",
        "original_text": "某工程队修筑公路，前3天共修筑4.48千米，后7天平均每天修筑1.36千米．这个工程队平均每天修筑公路多少千米？",
        "mask_text": "某 工程队 修筑公路 ， 前 N0 天共 修筑 N1 千米 ， 后 N2 天 平均 每天 修筑 N3 千米 ． 这个 工程队 平均 每天 修筑公路 多少 千米 ？",
        "context": "某工程队修筑公路，前3天共修筑4.48千米，后7天平均每天修筑1.36千米．",
        "original_question": "这个工程队平均每天修筑公路多少千米？",
        "nums": "3 4.48 7 1.36",
        "equ_unbias": {
            "N1": "",
            "N3": "",
            "N2": "",
            "N0": "",
            "N1 + N3": "",
            "N1 - N3": "",
            "N1 * N3": "",
            "N1 / N3": "",
            "N1 + N2": "",
            "N1 - N2": "",
            "N1 * N2": "",
            "N1 / N2": "",
            "N1 + N0": "",
            "N1 - N0": "",
            "N1 * N0": "",
            "N1 / N0": "",
            "N3 - N1": "",
            "N3 / N1": "",
            "N3 + N2": "",
            "N3 - N2": "",
            "N3 * N2": "",
            "N3 / N2": "",
            "N3 + N0": "",
            "N3 - N0": "",
            "N3 * N0": "",
            "N3 / N0": "",
            "N2 - N1": "",
            "N2 / N1": "",
            "N2 - N3": "",
            "N2 / N3": "",
            "N2 + N0": "",
            "N2 - N0": "",
            "N2 * N0": "",
            "N2 / N0": "",
            "N2 + N2": "",
            "N2 - N2": "",
            "N2 * N2": "",
            "N2 / N2": "",
            "N0 - N1": "",
            "N0 / N1": "",
            "N0 - N3": "",
            "N0 / N3": "",
            "N0 - N2": "",
            "N0 / N2": "",
            "N0 + N2": "",
            "N0 * N2": "",
            "N1 + ( N3 * N2 )": "",
            "( N1 + ( N3 * N2 ) ) / ( N0 + N2 )": "这个工程队平均每天修筑公路多少千米？",
            "N1 + ( N3 + N2 )": "",
            "N1 + ( N3 - N2 )": "",
            "N1 + ( N3 / N2 )": "",
            "N1 - ( N3 * N2 )": "",
            "N1 * ( N3 * N2 )": "",
            "N1 / ( N3 * N2 )": ""
        }
    },
    {
        "id": "6267",
        "original_text": "在一条公路一边从头至尾每隔6米架设一根电线杆，共用51根．这条公路全长多少米？",
        "mask_text": "在 一条 公路 一边 从头至尾 每隔 N0 米 架设 一根 电线杆 ， 共用 N1 根 ． 这 条 公路 全长 多少 米 ？",
        "context": "在一条公路一边从头至尾每隔6米架设一根电线杆，共用51根．",
        "original_question": "这条公路全长多少米？",
        "nums": "6 51",
        "equ_unbias": {
            "N0": "",
            "N1": "",
            "1": "",
            "N0 + N1": "",
            "N0 - N1": "",
            "N0 * N1": "",
            "N0 / N1": "",
            "N0 + 1": "",
            "N0 - 1": "",
            "N0 * 1": "",
            "N0 / 1": "",
            "N1 - N0": "",
            "N1 / N0": "",
            "N1 + 1": "",
            "N1 - 1": "",
            "N1 * 1": "",
            "N1 / 1": "",
            "1 - N0": "",
            "1 / N0": "",
            "1 - N1": "",
            "1 / N1": "",
            "N0 * ( N1 - 1 )": "这条公路全长多少米？",
            "N0 + ( N1 - 1 )": "",
            "N0 * ( N1 + 1 )": "",
            "N0 * ( N1 * 1 )": "",
            "N0 * ( N1 / 1 )": "",
            "N0 - ( N1 - 1 )": "",
            "N0 / ( N1 - 1 )": ""
        }
    },
    {
        "id": "15187",
        "original_text": "一件皮衣原价每件426元，现在降价(1/6)，现在每件售价多少元？",
        "mask_text": "一件 皮衣 原价 每件 N0 元 ， 现在 降价 N1 ， 现在 每件 售价 多少 元 ？",
        "context": "一件皮衣原价每件426元，现在降价(1/6)，",
        "original_question": "现在每件售价多少元？",
        "nums": "426 (1/6)",
        "equ_unbias": {
            "N0": "",
            "1": "",
            "N1": "",
            "N0 + 1": "",
            "N0 - 1": "",
            "N0 * 1": "",
            "N0 / 1": "",
            "N0 + N1": "",
            "N0 - N1": "",
            "N0 * N1": "",
            "N0 / N1": "",
            "1 - N0": "",
            "1 / N0": "",
            "1 + N1": "",
            "1 - N1": "",
            "1 * N1": "",
            "1 / N1": "",
            "N1 - N0": "",
            "N1 / N0": "",
            "N1 - 1": "",
            "N1 / 1": "",
            "N0 * ( 1 - N1 )": "现在每件售价多少元？",
            "N0 + ( 1 - N1 )": "",
            "N0 * ( 1 + N1 )": "",
            "N0 * ( 1 * N1 )": "",
            "N0 * ( 1 / N1 )": "",
            "N0 - ( 1 - N1 )": "",
            "N0 / ( 1 - N1 )": ""
        }
    },
    {
        "id": "5222",
        "original_text": "一块菜地的(5/9)种黄瓜，剩下的种茄子，种茄子的地占整块菜地的几分之几？",
        "mask_text": "一块 菜地 的 N0 种 黄瓜 ， 剩下 的 种 茄子 ， 种 茄子 的 地 占 整块 菜地 的 几分 之 几 ？",
        "context": "一块菜地的(5/9)种黄瓜，剩下的种茄子，",
        "original_question": "种茄子的地占整块菜地的几分之几？",
        "nums": "(5/9)",
        "equ_unbias": {
            "1": "",
            "N0": "",
            "1 + N0": "",
            "1 - N0": "种茄子的地占整块菜地的几分之几？",
            "1 * N0": "",
            "1 / N0": "",
            "N0 - 1": "",
            "N0 / 1": ""
        }
    },
    {
        "id": "5516",
        "original_text": "学校里组织兴趣小组，合唱队的人数是器乐队人数的3倍，舞蹈队的人数比器乐队少8人，舞蹈队有24人，合唱队有多少人？",
        "mask_text": "学校 里 组织 兴趣小组 ， 合唱队 的 人数 是 器 乐队 人数 的 N0 倍 ， 舞蹈队 的 人数 比器 乐队 少 N1 人 ， 舞蹈队 有 N2 人 ， 合唱队 有 多少 人 ？",
        "context": "学校里组织兴趣小组，合唱队的人数是器乐队人数的3倍，舞蹈队的人数比器乐队少8人，舞蹈队有24人，",
        "original_question": "合唱队有多少人？",
        "nums": "3 8 24",
        "equ_unbias": {
            "N2": "",
            "N1": "",
            "N0": "",
            "N2 + N1": "",
            "N2 - N1": "",
            "N2 * N1": "",
            "N2 / N1": "",
            "N2 + N0": "",
            "N2 - N0": "",
            "N2 * N0": "",
            "N2 / N0": "",
            "N1 - N2": "",
            "N1 / N2": "",
            "N1 + N0": "",
            "N1 - N0": "",
            "N1 * N0": "",
            "N1 / N0": "",
            "N0 - N2": "",
            "N0 / N2": "",
            "N0 - N1": "",
            "N0 / N1": "",
            "( N2 + N1 ) * N0": "合唱队有多少人？",
            "( N2 + N1 ) + N0": "",
            "( N2 + N1 ) - N0": "",
            "( N2 + N1 ) / N0": "",
            "( N2 - N1 ) * N0": "",
            "( N2 * N1 ) * N0": "",
            "( N2 / N1 ) * N0": ""
        }
    },
    {
        "id": "7641",
        "original_text": "某运输队计划用3天时间运一批货物，第一天运这批货物的(1/3)，第二天运这批货物的50%，还剩下120吨没运，这批货物一共有多少吨？",
        "mask_text": "某 运输队 计划 用 N0 天 时间 运 一批 货物 ， 第一天 运 这批 货物 的 N1 ， 第二天 运 这批 货物 的 N2 ， 还 剩下 N3 吨 没运 ， 这批 货物 一共 有 多少 吨 ？",
        "context": "某运输队计划用3天时间运一批货物，第一天运这批货物的(1/3)，第二天运这批货物的50%，还剩下120吨没运，",
        "original_question": "这批货物一共有多少吨？",
        "nums": "3 (1/3) 50% 120",
        "equ_unbias": {
            "N3": "",
            "1": "",
            "N1": "",
            "N2": "",
            "N3 + 1": "",
            "N3 - 1": "",
            "N3 * 1": "",
            "N3 / 1": "",
            "N3 + N1": "",
            "N3 - N1": "",
            "N3 * N1": "",
            "N3 / N1": "",
            "N3 + N2": "",
            "N3 - N2": "",
            "N3 * N2": "",
            "N3 / N2": "",
            "1 - N3": "",
            "1 / N3": "",
            "1 + N1": "",
            "1 - N1": "",
            "1 * N1": "",
            "1 / N1": "",
            "1 + N2": "",
            "1 - N2": "",
            "1 * N2": "",
            "1 / N2": "",
            "N1 - N3": "",
            "N1 / N3": "",
            "N1 - 1": "",
            "N1 / 1": "",
            "N1 + N2": "",
            "N1 - N2": "",
            "N1 * N2": "",
            "N1 / N2": "",
            "N2 - N3": "",
            "N2 / N3": "",
            "N2 - 1": "",
            "N2 / 1": "",
            "N2 - N1": "",
            "N2 / N1": "",
            "( 1 - N1 ) - N2": "",
            "N3 / ( ( 1 - N1 ) - N2 )": "这批货物一共有多少吨？",
            "( 1 + N1 ) - N2": "",
            "( 1 - N1 ) + N2": "",
            "( 1 - N1 ) * N2": "",
            "( 1 - N1 ) / N2": "",
            "( 1 * N1 ) - N2": "",
            "( 1 / N1 ) - N2": ""
        }
    },
    {
        "id": "6409",
        "original_text": "某居民小区有18幢楼房，每幢楼有8层，每层住6户人家，这个小区一共可住多少户人家？",
        "mask_text": "某 居民小区 有 N0 幢 楼房 ， 每幢 楼 有 N1 层 ， 每层 住 N2 户 人家 ， 这个 小区 一共 可住 多少 户 人家 ？",
        "context": "某居民小区有18幢楼房，每幢楼有8层，每层住6户人家，",
        "original_question": "这个小区一共可住多少户人家？",
        "nums": "18 8 6",
        "equ_unbias": {
            "N0": "",
            "N1": "",
            "N2": "",
            "N0 + N1": "",
            "N0 - N1": "",
            "N0 * N1": "",
            "N0 / N1": "",
            "N0 + N2": "",
            "N0 - N2": "",
            "N0 * N2": "",
            "N0 / N2": "",
            "N1 - N0": "",
            "N1 / N0": "",
            "N1 + N2": "",
            "N1 - N2": "",
            "N1 * N2": "",
            "N1 / N2": "",
            "N2 - N0": "",
            "N2 / N0": "",
            "N2 - N1": "",
            "N2 / N1": "",
            "( N0 * N1 ) * N2": "这个小区一共可住多少户人家？",
            "( N0 + N1 ) * N2": "",
            "( N0 * N1 ) + N2": "",
            "( N0 * N1 ) - N2": "",
            "( N0 * N1 ) / N2": "",
            "( N0 - N1 ) * N2": "",
            "( N0 / N1 ) * N2": ""
        }
    },
    {
        "id": "4638",
        "original_text": "小明两周看完了一本书，第一周看了132页，第二周看了这本书的56%，这本书一共有多少页？",
        "mask_text": "小明 两周 看 完 了 一 本书 ， 第一周 看 了 N0 页 ， 第二周 看 了 这 本书 的 N1 ， 这 本书 一共 有 多少 页 ？",
        "context": "小明两周看完了一本书，第一周看了132页，第二周看了这本书的56%，",
        "original_question": "这本书一共有多少页？",
        "nums": "132 56%",
        "equ_unbias": {
            "N0": "",
            "1": "",
            "N1": "",
            "N0 + 1": "",
            "N0 - 1": "",
            "N0 * 1": "",
            "N0 / 1": "",
            "N0 + N1": "",
            "N0 - N1": "",
            "N0 * N1": "",
            "N0 / N1": "",
            "1 - N0": "",
            "1 / N0": "",
            "1 + N1": "",
            "1 - N1": "",
            "1 * N1": "",
            "1 / N1": "",
            "N1 - N0": "",
            "N1 / N0": "",
            "N1 - 1": "",
            "N1 / 1": "",
            "N0 / ( 1 - N1 )": "这本书一共有多少页？",
            "N0 + ( 1 - N1 )": "",
            "N0 / ( 1 + N1 )": "",
            "N0 / ( 1 * N1 )": "",
            "N0 / ( 1 / N1 )": "",
            "N0 - ( 1 - N1 )": "",
            "N0 * ( 1 - N1 )": ""
        }
    },
    {
        "id": "10165",
        "original_text": "实验小学五年级有5个班，每班捐30盆花，布置花坛用去了若干盆后还剩25盆，布置花坛用去多少盆？",
        "mask_text": "实验 小学 五年级 有 N0 个班 ， 每班 捐 N1 盆花 ， 布置 花坛 用 去 了 若干 盆后 还 剩 N2 盆 ， 布置 花坛 用 去 多少 盆 ？",
        "context": "实验小学五年级有5个班，每班捐30盆花，布置花坛用去了若干盆后还剩25盆，",
        "original_question": "布置花坛用去多少盆？",
        "nums": "5 30 25",
        "equ_unbias": {
            "N1": "",
            "N0": "",
            "N2": "",
            "N1 + N0": "",
            "N1 - N0": "",
            "N1 * N0": "",
            "N1 / N0": "",
            "N1 + N2": "",
            "N1 - N2": "",
            "N1 * N2": "",
            "N1 / N2": "",
            "N0 - N1": "",
            "N0 / N1": "",
            "N0 + N2": "",
            "N0 - N2": "",
            "N0 * N2": "",
            "N0 / N2": "",
            "N2 - N1": "",
            "N2 / N1": "",
            "N2 - N0": "",
            "N2 / N0": "",
            "( N1 * N0 ) - N2": "布置花坛用去多少盆？",
            "( N1 + N0 ) - N2": "",
            "( N1 * N0 ) + N2": "",
            "( N1 * N0 ) * N2": "",
            "( N1 * N0 ) / N2": "",
            "( N1 - N0 ) - N2": "",
            "( N1 / N0 ) - N2": ""
        }
    },
    {
        "id": "825",
        "original_text": "果品公司运来205筐水果，有120筐是香蕉，其余的是芒果，香蕉比芒果多多少筐？",
        "mask_text": "果品 公司 运来 N0 筐 水果 ， 有 N1 筐 是 香蕉 ， 其余 的 是 芒果 ， 香蕉 比 芒果 多 多少 筐 ？",
        "context": "果品公司运来205筐水果，有120筐是香蕉，其余的是芒果，",
        "original_question": "香蕉比芒果多多少筐？",
        "nums": "205 120",
        "equ_unbias": {
            "N1": "",
            "N0": "",
            "N1 + N0": "",
            "N1 - N0": "",
            "N1 * N0": "",
            "N1 / N0": "",
            "N1 + N1": "",
            "N1 - N1": "",
            "N1 * N1": "",
            "N1 / N1": "",
            "N0 - N1": "",
            "N0 / N1": "",
            "N0 + N1": "",
            "N0 * N1": "",
            "N1 - ( N0 - N1 )": "香蕉比芒果多多少筐？",
            "N1 + ( N0 - N1 )": "",
            "N1 - ( N0 + N1 )": "",
            "N1 - ( N0 * N1 )": "",
            "N1 - ( N0 / N1 )": "",
            "N1 * ( N0 - N1 )": "",
            "N1 / ( N0 - N1 )": ""
        }
    },
    {
        "id": "10831",
        "original_text": "前进乡计划挖一条300米长的水渠，已经挖了(4/5)，还剩下多少米没挖？",
        "mask_text": "前进 乡 计划 挖 一条 N0 米长 的 水渠 ， 已经 挖 了 N1 ， 还 剩下 多少 米 没 挖 ？",
        "context": "前进乡计划挖一条300米长的水渠，已经挖了(4/5)，",
        "original_question": "还剩下多少米没挖？",
        "nums": "300 (4/5)",
        "equ_unbias": {
            "N0": "",
            "1": "",
            "N1": "",
            "N0 + 1": "",
            "N0 - 1": "",
            "N0 * 1": "",
            "N0 / 1": "",
            "N0 + N1": "",
            "N0 - N1": "",
            "N0 * N1": "",
            "N0 / N1": "",
            "1 - N0": "",
            "1 / N0": "",
            "1 + N1": "",
            "1 - N1": "",
            "1 * N1": "",
            "1 / N1": "",
            "N1 - N0": "",
            "N1 / N0": "",
            "N1 - 1": "",
            "N1 / 1": "",
            "N0 * ( 1 - N1 )": "还剩下多少米没挖？",
            "N0 + ( 1 - N1 )": "",
            "N0 * ( 1 + N1 )": "",
            "N0 * ( 1 * N1 )": "",
            "N0 * ( 1 / N1 )": "",
            "N0 - ( 1 - N1 )": "",
            "N0 / ( 1 - N1 )": ""
        }
    }
]