[
    {
        "id": "a8bef293be8c11eb831704d4c4250d10",
        "original_text": "雨母山森林公园有128公顷森林。1公顷森林一年可滞尘32吨，一天可从地下吸出85吨水。则雨母山森林公园一天可以吸水多少吨？",
        "mask_text": "雨母山 森林公园 有 N0 公顷 森林 。 N1 公顷 森林 一年 可滞尘 N2 吨 ， 一天 可 从 地下 吸出 N3 吨 水 。 则 雨 母山 森林公园 一天 可以 吸水 多少 吨 ？",
        "context": "雨母山森林公园有128公顷森林。1公顷森林一年可滞尘32吨，一天可从地下吸出85吨水。",
        "original_question": "则雨母山森林公园一天可以吸水多少吨？",
        "nums": "128 1 32 85",
        "equ_unbias": {
            "N0": "",
            "N3": "",
            "N0 + N3": "",
            "N0 - N3": "",
            "N0 * N3": "则雨母山森林公园一天可以吸水多少吨？",
            "N0 / N3": "",
            "N3 - N0": "",
            "N3 / N0": ""
        }
    },
    {
        "id": "a2626d06be8c11ebbd5604d4c4250d10",
        "original_text": "用1000个鸡蛋孵小鸡，上午孵出了437只小鸡，下午比上午少孵出108只。下午孵出了多少只小鸡？",
        "mask_text": "用 N0 个 鸡蛋 孵小鸡 ， 上午 孵出 了 N1 只 小鸡 ， 下午 比 上午 少 孵出 N2 只 。 下午 孵出 了 多少 只 小鸡 ？",
        "context": "用1000个鸡蛋孵小鸡，上午孵出了437只小鸡，下午比上午少孵出108只。",
        "original_question": "下午孵出了多少只小鸡？",
        "nums": "1000 437 108",
        "equ_unbias": {
            "N1": "",
            "N2": "",
            "N1 + N2": "",
            "N1 - N2": "下午孵出了多少只小鸡？",
            "N1 * N2": "",
            "N1 / N2": "",
            "N2 - N1": "",
            "N2 / N1": ""
        }
    },
    {
        "id": "a56256d3be8c11eba7f504d4c4250d10",
        "original_text": "王阿姨得到一笔3200元的劳务费，其中800元是免税的，其余部分按20%的税率缴税．这笔劳务费一共要缴税多少钱？",
        "mask_text": "王 阿姨 得到 一笔 N0 元 的 劳务费 ， 其中 N1 元 是 免税 的 ， 其余部分 按 N2 的 税率 缴税 ． 这笔 劳务费 一共 要 缴税 多少 钱 ？",
        "context": "王阿姨得到一笔3200元的劳务费，其中800元是免税的，其余部分按20%的税率缴税．",
        "original_question": "这笔劳务费一共要缴税多少钱？",
        "nums": "3200 800 20%",
        "equ_unbias": {
            "N0": "",
            "N1": "",
            "N2": "",
            "N0 + N1": "",
            "N0 - N1": "",
            "N0 * N1": "",
            "N0 / N1": "",
            "N0 + N2": "",
            "N0 - N2": "",
            "N0 * N2": "",
            "N0 / N2": "",
            "N1 - N0": "",
            "N1 / N0": "",
            "N1 + N2": "",
            "N1 - N2": "",
            "N1 * N2": "",
            "N1 / N2": "",
            "N2 - N0": "",
            "N2 / N0": "",
            "N2 - N1": "",
            "N2 / N1": "",
            "( N0 - N1 ) * N2": "这笔劳务费一共要缴税多少钱？",
            "( N0 + N1 ) * N2": "",
            "( N0 - N1 ) + N2": "",
            "( N0 - N1 ) - N2": "",
            "( N0 - N1 ) / N2": "",
            "( N0 * N1 ) * N2": "",
            "( N0 / N1 ) * N2": ""
        }
    },
    {
        "id": "a628a6c5be8c11eb811c04d4c4250d10",
        "original_text": "五年级某班在组织大扫除时，如果6人一组或7人一组都正好分完，且没有剩余的人，这个班至少有多少人？",
        "mask_text": "五年级 某班 在 组织 大扫除 时 ， 如果 N0 人 一组 或 N1 人 一组 都 正好 分完 ， 且 没有 剩余 的 人 ， 这个 班 至少 有 多少 人 ？",
        "context": "五年级某班在组织大扫除时，如果6人一组或7人一组都正好分完，且没有剩余的人，",
        "original_question": "这个班至少有多少人？",
        "nums": "6 7",
        "equ_unbias": {
            "N0": "",
            "N1": "",
            "N0 + N1": "",
            "N0 - N1": "",
            "N0 * N1": "这个班至少有多少人？",
            "N0 / N1": "",
            "N1 - N0": "",
            "N1 / N0": ""
        }
    },
    {
        "id": "a15af41bbe8c11eba05d04d4c4250d10",
        "original_text": "某水果店上午卖了20千克苹果，下午卖了24千克苹果，如果每千克苹果5元，一共可卖多少元？",
        "mask_text": "某 水果店 上午 卖 了 N0 千克 苹果 ， 下午 卖 了 N1 千克 苹果 ， 如果 每千克 苹果 N2 元 ， 一共 可卖 多少 元 ？",
        "context": "某水果店上午卖了20千克苹果，下午卖了24千克苹果，如果每千克苹果5元，",
        "original_question": "一共可卖多少元？",
        "nums": "20 24 5",
        "equ_unbias": {
            "N0": "",
            "N1": "",
            "N2": "",
            "N0 + N1": "",
            "N0 - N1": "",
            "N0 * N1": "",
            "N0 / N1": "",
            "N0 + N2": "",
            "N0 - N2": "",
            "N0 * N2": "",
            "N0 / N2": "",
            "N1 - N0": "",
            "N1 / N0": "",
            "N1 + N2": "",
            "N1 - N2": "",
            "N1 * N2": "",
            "N1 / N2": "",
            "N2 - N0": "",
            "N2 / N0": "",
            "N2 - N1": "",
            "N2 / N1": "",
            "( N0 + N1 ) * N2": "一共可卖多少元？",
            "( N0 + N1 ) + N2": "",
            "( N0 + N1 ) - N2": "",
            "( N0 + N1 ) / N2": "",
            "( N0 - N1 ) * N2": "",
            "( N0 * N1 ) * N2": "",
            "( N0 / N1 ) * N2": ""
        }
    },
    {
        "id": "a3a77d66be8c11ebaf4604d4c4250d10",
        "original_text": "王明宇爸爸的张庄大酒店每月的营业额大约为120万元，按规定除了按营业额的5%缴纳营业税以外，还要按营业税的7%缴纳城市维护建设税，那么需要交纳这两种税共多少万元？",
        "mask_text": "王明 宇 爸爸 的 张庄 大酒店 每月 的 营业额 大约 为 N0 万元 ， 按规定 除了 按 营业额 的 N1 缴纳 营业税 以外 ， 还要 按 营业税 的 N2 缴纳 城市 维护 建设 税 ， 那么 需要 交纳 这 两种 税共 多少 万元 ？",
        "context": "王明宇爸爸的张庄大酒店每月的营业额大约为120万元，按规定除了按营业额的5%缴纳营业税以外，还要按营业税的7%缴纳城市维护建设税，",
        "original_question": "那么需要交纳这两种税共多少万元？",
        "nums": "120 5% 7%",
        "equ_unbias": {
            "N0": "",
            "N1": "",
            "N2": "",
            "N0 + N1": "",
            "N0 - N1": "",
            "N0 * N1": "",
            "N0 / N1": "",
            "N0 + N0": "",
            "N0 - N0": "",
            "N0 * N0": "",
            "N0 / N0": "",
            "N0 + N2": "",
            "N0 - N2": "",
            "N0 * N2": "",
            "N0 / N2": "",
            "N1 - N0": "",
            "N1 / N0": "",
            "N1 + N0": "",
            "N1 * N0": "",
            "N1 + N1": "",
            "N1 - N1": "",
            "N1 * N1": "",
            "N1 / N1": "",
            "N1 + N2": "",
            "N1 - N2": "",
            "N1 * N2": "",
            "N1 / N2": "",
            "N2 - N0": "",
            "N2 / N0": "",
            "N2 - N1": "",
            "N2 / N1": "",
            "( N0 * N1 ) * N2": "",
            "( N0 * N1 ) + ( ( N0 * N1 ) * N2 )": "那么需要交纳这两种税共多少万元？",
            "( N0 + N1 ) * N2": "",
            "( N0 * N1 ) + N2": "",
            "( N0 * N1 ) - N2": "",
            "( N0 * N1 ) / N2": "",
            "( N0 - N1 ) * N2": "",
            "( N0 / N1 ) * N2": ""
        }
    },
    {
        "id": "9de3cc19be8c11eb9fa404d4c4250d10",
        "original_text": "一个燃气灶的包装箱长0.8米，宽0.4米，高0.15米．这个包装箱的体积是多少立方米？",
        "mask_text": "一个 燃气灶 的 包装箱 长 N0 米 ， 宽 N1 米 ， 高 N2 米 ． 这个 包装箱 的 体积 是 多少 立方米 ？",
        "context": "一个燃气灶的包装箱长0.8米，宽0.4米，高0.15米．",
        "original_question": "这个包装箱的体积是多少立方米？",
        "nums": "0.8 0.4 0.15",
        "equ_unbias": {
            "N0": "",
            "N1": "",
            "N2": "",
            "N0 + N1": "",
            "N0 - N1": "",
            "N0 * N1": "",
            "N0 / N1": "",
            "N0 + N2": "",
            "N0 - N2": "",
            "N0 * N2": "",
            "N0 / N2": "",
            "N1 - N0": "",
            "N1 / N0": "",
            "N1 + N2": "",
            "N1 - N2": "",
            "N1 * N2": "",
            "N1 / N2": "",
            "N2 - N0": "",
            "N2 / N0": "",
            "N2 - N1": "",
            "N2 / N1": "",
            "( N0 * N1 ) * N2": "这个包装箱的体积是多少立方米？",
            "( N0 + N1 ) * N2": "",
            "( N0 * N1 ) + N2": "",
            "( N0 * N1 ) - N2": "",
            "( N0 * N1 ) / N2": "",
            "( N0 - N1 ) * N2": "",
            "( N0 / N1 ) * N2": ""
        }
    },
    {
        "id": "a98de9ecbe8c11ebad8304d4c4250d10",
        "original_text": "一本故事书有856页，小军看了一些，还剩237页，看了的页数比剩下的多多少页？",
        "mask_text": "一本 故事书 有 N0 页 ， 小军 看 了 一些 ， 还 剩 N1 页 ， 看 了 的 页数 比 剩下 的 多 多少 页 ？",
        "context": "一本故事书有856页，小军看了一些，还剩237页，",
        "original_question": "看了的页数比剩下的多多少页？",
        "nums": "856 237",
        "equ_unbias": {
            "N0": "",
            "N1": "",
            "N0 + N1": "",
            "N0 - N1": "",
            "N0 * N1": "",
            "N0 / N1": "",
            "N1 - N0": "",
            "N1 / N0": "",
            "N1 + N1": "",
            "N1 - N1": "",
            "N1 * N1": "",
            "N1 / N1": "",
            "( N0 - N1 ) - N1": "看了的页数比剩下的多多少页？",
            "( N0 + N1 ) - N1": "",
            "( N0 - N1 ) + N1": "",
            "( N0 - N1 ) * N1": "",
            "( N0 - N1 ) / N1": "",
            "( N0 * N1 ) - N1": "",
            "( N0 / N1 ) - N1": ""
        }
    },
    {
        "id": "a507caa2be8c11ebbac304d4c4250d10",
        "original_text": "2017年11月张爷爷把儿子寄来的800元钱存入银行，存期3年．年利率为2.75%，一共能取回多少钱？",
        "mask_text": "N0 年 N1 月 张 爷爷 把 儿子 寄来 的 N2 元 钱 存入 银行 ， 存期 N3 年 ． 年利率 为 N4 ， 一共 能 取回 多少 钱 ？",
        "context": "2017年11月张爷爷把儿子寄来的800元钱存入银行，存期3年．年利率为2.75%，",
        "original_question": "一共能取回多少钱？",
        "nums": "2017 11 800 3 2.75%",
        "equ_unbias": {
            "N2": "",
            "N4": "",
            "N3": "",
            "N2 + N4": "",
            "N2 - N4": "",
            "N2 * N4": "",
            "N2 / N4": "",
            "N2 + N3": "",
            "N2 - N3": "",
            "N2 * N3": "",
            "N2 / N3": "",
            "N2 + N2": "",
            "N2 - N2": "",
            "N2 * N2": "",
            "N2 / N2": "",
            "N4 - N2": "",
            "N4 / N2": "",
            "N4 + N3": "",
            "N4 - N3": "",
            "N4 * N3": "",
            "N4 / N3": "",
            "N4 + N2": "",
            "N4 * N2": "",
            "N3 - N2": "",
            "N3 / N2": "",
            "N3 - N4": "",
            "N3 / N4": "",
            "N3 + N2": "",
            "N3 * N2": "",
            "( N2 * N4 ) * N3": "",
            "( ( N2 * N4 ) * N3 ) + N2": "一共能取回多少钱？",
            "( N2 + N4 ) * N3": "",
            "( N2 * N4 ) + N3": "",
            "( N2 * N4 ) - N3": "",
            "( N2 * N4 ) / N3": "",
            "( N2 - N4 ) * N3": "",
            "( N2 / N4 ) * N3": ""
        }
    },
    {
        "id": "9fe2e7b2be8c11eb860b04d4c4250d10",
        "original_text": "去年植树节三年级同学上午种树14行,下午种树13行,平均每行种28棵树,三年级同学一共种树多少棵?",
        "mask_text": "去年 植树节 三年级 同学 上午 种树 N0 行 , 下午 种树 N1 行 , 平均 每行 种 N2 棵 树 , 三年级 同学 一共 种树 多少 棵 ?",
        "context": "去年植树节三年级同学上午种树14行,下午种树13行,平均每行种28棵树,",
        "original_question": "三年级同学一共种树多少棵?",
        "nums": "14 13 28",
        "equ_unbias": {
            "N0": "",
            "N1": "",
            "N2": "",
            "N0 + N1": "",
            "N0 - N1": "",
            "N0 * N1": "",
            "N0 / N1": "",
            "N0 + N2": "",
            "N0 - N2": "",
            "N0 * N2": "",
            "N0 / N2": "",
            "N1 - N0": "",
            "N1 / N0": "",
            "N1 + N2": "",
            "N1 - N2": "",
            "N1 * N2": "",
            "N1 / N2": "",
            "N2 - N0": "",
            "N2 / N0": "",
            "N2 - N1": "",
            "N2 / N1": "",
            "( N0 + N1 ) * N2": "三年级同学一共种树多少棵?",
            "( N0 + N1 ) + N2": "",
            "( N0 + N1 ) - N2": "",
            "( N0 + N1 ) / N2": "",
            "( N0 - N1 ) * N2": "",
            "( N0 * N1 ) * N2": "",
            "( N0 / N1 ) * N2": ""
        }
    },
    {
        "id": "a9370605be8c11eba00304d4c4250d10",
        "original_text": "宝剑山小学组织环保活动，三年级同学收集垃圾245千克，四年级同学收集垃圾362千克，五年级同学收集的垃圾比三、四年级收集的垃圾之和少168千克，三、四、五年级的同学总共收集垃圾多少千克？",
        "mask_text": "宝剑 山 小学 组织 环保 活动 ， 三年级 同学 收集 垃圾 N0 千克 ， 四年级 同学 收集 垃圾 N1 千克 ， 五年级 同学 收集 的 垃圾 比三 、 四年级 收集 的 垃圾 之和少 N2 千克 ， 三 、 四 、 五年级 的 同学 总共 收集 垃圾 多少 千克 ？",
        "context": "宝剑山小学组织环保活动，三年级同学收集垃圾245千克，四年级同学收集垃圾362千克，五年级同学收集的垃圾比三、四年级收集的垃圾之和少168千克，",
        "original_question": "三、四、五年级的同学总共收集垃圾多少千克？",
        "nums": "245 362 168",
        "equ_unbias": {
            "N0": "",
            "N1": "",
            "N2": "",
            "N0 + N1": "",
            "N0 - N1": "",
            "N0 * N1": "",
            "N0 / N1": "",
            "N0 + N2": "",
            "N0 - N2": "",
            "N0 * N2": "",
            "N0 / N2": "",
            "N0 + N0": "",
            "N0 - N0": "",
            "N0 * N0": "",
            "N0 / N0": "",
            "N1 - N0": "",
            "N1 / N0": "",
            "N1 + N2": "",
            "N1 - N2": "",
            "N1 * N2": "",
            "N1 / N2": "",
            "N1 + N0": "",
            "N1 * N0": "",
            "N1 + N1": "",
            "N1 - N1": "",
            "N1 * N1": "",
            "N1 / N1": "",
            "N2 - N0": "",
            "N2 / N0": "",
            "N2 - N1": "",
            "N2 / N1": "",
            "N2 + N0": "",
            "N2 * N0": "",
            "N2 + N1": "",
            "N2 * N1": "",
            "( N0 + N1 ) - N2": "",
            "( ( N0 + N1 ) - N2 ) + N0": "",
            "( ( ( N0 + N1 ) - N2 ) + N0 ) + N1": "三、四、五年级的同学总共收集垃圾多少千克？",
            "( N0 + N1 ) + N2": "",
            "( N0 + N1 ) * N2": "",
            "( N0 + N1 ) / N2": "",
            "( N0 - N1 ) - N2": "",
            "( N0 * N1 ) - N2": "",
            "( N0 / N1 ) - N2": ""
        }
    },
    {
        "id": "a366d016be8c11eb9bbe04d4c4250d10",
        "original_text": "修路队要修筑一段公路，已经修了4天，平均每天修69米，剩下的是已经修好的8倍，这段公路还有多少米没有修？",
        "mask_text": "修路 队要 修筑 一段 公路 ， 已经 修 了 N0 天 ， 平均 每天 修 N1 米 ， 剩下 的 是 已经 修好 的 N2 倍 ， 这 段 公路 还有 多少 米 没有 修 ？",
        "context": "修路队要修筑一段公路，已经修了4天，平均每天修69米，剩下的是已经修好的8倍，",
        "original_question": "这段公路还有多少米没有修？",
        "nums": "4 69 8",
        "equ_unbias": {
            "N1": "",
            "N0": "",
            "N2": "",
            "N1 + N0": "",
            "N1 - N0": "",
            "N1 * N0": "",
            "N1 / N0": "",
            "N1 + N2": "",
            "N1 - N2": "",
            "N1 * N2": "",
            "N1 / N2": "",
            "N0 - N1": "",
            "N0 / N1": "",
            "N0 + N2": "",
            "N0 - N2": "",
            "N0 * N2": "",
            "N0 / N2": "",
            "N2 - N1": "",
            "N2 / N1": "",
            "N2 - N0": "",
            "N2 / N0": "",
            "( N1 * N0 ) * N2": "这段公路还有多少米没有修？",
            "( N1 + N0 ) * N2": "",
            "( N1 * N0 ) + N2": "",
            "( N1 * N0 ) - N2": "",
            "( N1 * N0 ) / N2": "",
            "( N1 - N0 ) * N2": "",
            "( N1 / N0 ) * N2": ""
        }
    },
    {
        "id": "a4cd5a97be8c11eba97204d4c4250d10",
        "original_text": "张奶奶把儿子寄来的1500元钱存入银行，存期为5年，年利率为2.75%．到期支取时，到期时张奶奶一共能取回多少钱？",
        "mask_text": "张 奶奶 把 儿子 寄来 的 N0 元 钱 存入 银行 ， 存期 为 N1 年 ， 年利率 为 N2 ． 到期 支取 时 ， 到期 时张 奶奶 一共 能 取回 多少 钱 ？",
        "context": "张奶奶把儿子寄来的1500元钱存入银行，存期为5年，年利率为2.75%．到期支取时，",
        "original_question": "到期时张奶奶一共能取回多少钱？",
        "nums": "1500 5 2.75%",
        "equ_unbias": {
            "N0": "",
            "N2": "",
            "N1": "",
            "N0 + N0": "",
            "N0 - N0": "",
            "N0 * N0": "",
            "N0 / N0": "",
            "N0 + N2": "",
            "N0 - N2": "",
            "N0 * N2": "",
            "N0 / N2": "",
            "N0 + N1": "",
            "N0 - N1": "",
            "N0 * N1": "",
            "N0 / N1": "",
            "N2 - N0": "",
            "N2 / N0": "",
            "N2 + N1": "",
            "N2 - N1": "",
            "N2 * N1": "",
            "N2 / N1": "",
            "N1 - N0": "",
            "N1 / N0": "",
            "N1 - N2": "",
            "N1 / N2": "",
            "( N0 * N2 ) * N1": "",
            "N0 + ( ( N0 * N2 ) * N1 )": "到期时张奶奶一共能取回多少钱？",
            "( N0 + N2 ) * N1": "",
            "( N0 * N2 ) + N1": "",
            "( N0 * N2 ) - N1": "",
            "( N0 * N2 ) / N1": "",
            "( N0 - N2 ) * N1": "",
            "( N0 / N2 ) * N1": ""
        }
    },
    {
        "id": "a999c8abbe8c11eb801d04d4c4250d10",
        "original_text": "王伯伯的菜地里今年收获了832千克西红柿、528千克萝卜和498千克白菜．一共收获多少千克蔬菜？",
        "mask_text": "王 伯伯 的 菜地 里 今年 收获 了 N0 千克 西红柿 、 N1 千克 萝卜 和 N2 千克 白菜 ． 一共 收获 多少 千克 蔬菜 ？",
        "context": "王伯伯的菜地里今年收获了832千克西红柿、528千克萝卜和498千克白菜．",
        "original_question": "一共收获多少千克蔬菜？",
        "nums": "832 528 498",
        "equ_unbias": {
            "N0": "",
            "N1": "",
            "N2": "",
            "N0 + N1": "",
            "N0 - N1": "",
            "N0 * N1": "",
            "N0 / N1": "",
            "N0 + N2": "",
            "N0 - N2": "",
            "N0 * N2": "",
            "N0 / N2": "",
            "N1 - N0": "",
            "N1 / N0": "",
            "N1 + N2": "",
            "N1 - N2": "",
            "N1 * N2": "",
            "N1 / N2": "",
            "N2 - N0": "",
            "N2 / N0": "",
            "N2 - N1": "",
            "N2 / N1": "",
            "( N0 + N1 ) + N2": "一共收获多少千克蔬菜？",
            "( N0 + N1 ) - N2": "",
            "( N0 + N1 ) * N2": "",
            "( N0 + N1 ) / N2": "",
            "( N0 - N1 ) + N2": "",
            "( N0 * N1 ) + N2": "",
            "( N0 / N1 ) + N2": ""
        }
    },
    {
        "id": "aa1f661dbe8c11eb8a9004d4c4250d10",
        "original_text": "超市上午运来535个鸡蛋，上午卖出376个，下午又运来212个，现在超市有多少个鸡蛋？",
        "mask_text": "超市 上午 运来 N0 个 鸡蛋 ， 上午 卖出 N1 个 ， 下午 又 运来 N2 个 ， 现在 超市 有 多少 个 鸡蛋 ？",
        "context": "超市上午运来535个鸡蛋，上午卖出376个，下午又运来212个，",
        "original_question": "现在超市有多少个鸡蛋？",
        "nums": "535 376 212",
        "equ_unbias": {
            "N0": "",
            "N1": "",
            "N2": "",
            "N0 + N1": "",
            "N0 - N1": "",
            "N0 * N1": "",
            "N0 / N1": "",
            "N0 + N2": "",
            "N0 - N2": "",
            "N0 * N2": "",
            "N0 / N2": "",
            "N1 - N0": "",
            "N1 / N0": "",
            "N1 + N2": "",
            "N1 - N2": "",
            "N1 * N2": "",
            "N1 / N2": "",
            "N2 - N0": "",
            "N2 / N0": "",
            "N2 - N1": "",
            "N2 / N1": "",
            "( N0 - N1 ) + N2": "现在超市有多少个鸡蛋？",
            "( N0 + N1 ) + N2": "",
            "( N0 - N1 ) - N2": "",
            "( N0 - N1 ) * N2": "",
            "( N0 - N1 ) / N2": "",
            "( N0 * N1 ) + N2": "",
            "( N0 / N1 ) + N2": ""
        }
    },
    {
        "id": "a181ebbcbe8c11eb8e4304d4c4250d10",
        "original_text": "一条裙子130元，一件上衣的价格正好是裙子的4倍。买一条裙子和一件上衣一共多少钱？",
        "mask_text": "一条 裙子 N0 元 ， 一件 上衣 的 价格 正好 是 裙子 的 N1 倍 。 买 一条 裙子 和 一件 上衣 一共 多少 钱 ？",
        "context": "一条裙子130元，一件上衣的价格正好是裙子的4倍。",
        "original_question": "买一条裙子和一件上衣一共多少钱？",
        "nums": "130 4",
        "equ_unbias": {
            "N0": "",
            "N1": "",
            "N0 + N1": "",
            "N0 - N1": "",
            "N0 * N1": "",
            "N0 / N1": "",
            "N0 + N0": "",
            "N0 - N0": "",
            "N0 * N0": "",
            "N0 / N0": "",
            "N1 - N0": "",
            "N1 / N0": "",
            "N1 + N0": "",
            "N1 * N0": "",
            "( N0 * N1 ) + N0": "买一条裙子和一件上衣一共多少钱？",
            "( N0 + N1 ) + N0": "",
            "( N0 * N1 ) - N0": "",
            "( N0 * N1 ) * N0": "",
            "( N0 * N1 ) / N0": "",
            "( N0 - N1 ) + N0": "",
            "( N0 / N1 ) + N0": ""
        }
    },
    {
        "id": "9f75a1c9be8c11ebab8004d4c4250d10",
        "original_text": "女同学有39人，男同学有41人．4个同学分成一组，可以分成几个小组？",
        "mask_text": "女同学 有 N0 人 ， 男同学 有 N1 人 ． N2 个 同学 分成 一组 ， 可以 分成 几个 小组 ？",
        "context": "女同学有39人，男同学有41人．4个同学分成一组，",
        "original_question": "可以分成几个小组？",
        "nums": "39 41 4",
        "equ_unbias": {
            "N0": "",
            "N1": "",
            "N2": "",
            "N0 + N1": "",
            "N0 - N1": "",
            "N0 * N1": "",
            "N0 / N1": "",
            "N0 + N2": "",
            "N0 - N2": "",
            "N0 * N2": "",
            "N0 / N2": "",
            "N1 - N0": "",
            "N1 / N0": "",
            "N1 + N2": "",
            "N1 - N2": "",
            "N1 * N2": "",
            "N1 / N2": "",
            "N2 - N0": "",
            "N2 / N0": "",
            "N2 - N1": "",
            "N2 / N1": "",
            "( N0 + N1 ) / N2": "可以分成几个小组？",
            "( N0 + N1 ) + N2": "",
            "( N0 + N1 ) - N2": "",
            "( N0 + N1 ) * N2": "",
            "( N0 - N1 ) / N2": "",
            "( N0 * N1 ) / N2": "",
            "( N0 / N1 ) / N2": ""
        }
    },
    {
        "id": "a597e823be8c11ebb87404d4c4250d10",
        "original_text": "妈妈每天饭后步行1000米，她1分钟能步行198米，5分钟能步行多少米？",
        "mask_text": "妈妈 每天 饭后 步行 N0 米 ， 她 N1 分钟 能 步行 N2 米 ， N3 分钟 能 步行 多少 米 ？",
        "context": "妈妈每天饭后步行1000米，她1分钟能步行198米，",
        "original_question": "5分钟能步行多少米？",
        "nums": "1000 1 198 5",
        "equ_unbias": {
            "N2": "",
            "N3": "",
            "N2 + N3": "",
            "N2 - N3": "",
            "N2 * N3": "5分钟能步行多少米？",
            "N2 / N3": "",
            "N3 - N2": "",
            "N3 / N2": ""
        }
    },
    {
        "id": "a1292f80be8c11eba8b804d4c4250d10",
        "original_text": "2012年11月赵华把1000元存入银行，定期2年．如果年利率按3.75%计算，到期后，她可以取出本金和利息一共多少元？",
        "mask_text": "N0 年 N1 月 赵华 把 N2 元 存入 银行 ， 定期 N3 年 ． 如果 年利率 按 N4 计算 ， 到期 后 ， 她 可以 取出 本金 和 利息 一共 多少 元 ？",
        "context": "2012年11月赵华把1000元存入银行，定期2年．如果年利率按3.75%计算，到期后，",
        "original_question": "她可以取出本金和利息一共多少元？",
        "nums": "2012 11 1000 2 3.75%",
        "equ_unbias": {
            "N2": "",
            "N4": "",
            "N3": "",
            "N2 + N2": "",
            "N2 - N2": "",
            "N2 * N2": "",
            "N2 / N2": "",
            "N2 + N4": "",
            "N2 - N4": "",
            "N2 * N4": "",
            "N2 / N4": "",
            "N2 + N3": "",
            "N2 - N3": "",
            "N2 * N3": "",
            "N2 / N3": "",
            "N4 - N2": "",
            "N4 / N2": "",
            "N4 + N3": "",
            "N4 - N3": "",
            "N4 * N3": "",
            "N4 / N3": "",
            "N3 - N2": "",
            "N3 / N2": "",
            "N3 - N4": "",
            "N3 / N4": "",
            "( N2 * N4 ) * N3": "",
            "N2 + ( ( N2 * N4 ) * N3 )": "她可以取出本金和利息一共多少元？",
            "( N2 + N4 ) * N3": "",
            "( N2 * N4 ) + N3": "",
            "( N2 * N4 ) - N3": "",
            "( N2 * N4 ) / N3": "",
            "( N2 - N4 ) * N3": "",
            "( N2 / N4 ) * N3": ""
        }
    },
    {
        "id": "a5d64e2bbe8c11eb9ab904d4c4250d10",
        "original_text": "妈妈买了一袋25㎏的大米，用去70.5元．你知道平均每千克大米多少钱吗？",
        "mask_text": "妈妈 买 了 一袋 N0 ㎏ 的 大米 ， 用 去 N1 元 ． 你 知道 平均 每千克 大米 多少 钱 吗 ？",
        "context": "妈妈买了一袋25㎏的大米，用去70.5元．",
        "original_question": "你知道平均每千克大米多少钱吗？",
        "nums": "25 70.5",
        "equ_unbias": {
            "N1": "",
            "N0": "",
            "N1 + N0": "",
            "N1 - N0": "",
            "N1 * N0": "",
            "N1 / N0": "你知道平均每千克大米多少钱吗？",
            "N0 - N1": "",
            "N0 / N1": ""
        }
    },
    {
        "id": "a203ebddbe8c11eba44004d4c4250d10",
        "original_text": "供电局原来有捆电线长14.85米，工人师傅第一次用去0.75米，第二次又用去1.25米，这时电线还剩多少米？",
        "mask_text": "供电局 原来 有 捆 电线 长 N0 米 ， 工人 师傅 第一次 用 去 N1 米 ， 第二次 又 用 去 N2 米 ， 这时 电线 还 剩 多少 米 ？",
        "context": "供电局原来有捆电线长14.85米，工人师傅第一次用去0.75米，第二次又用去1.25米，",
        "original_question": "这时电线还剩多少米？",
        "nums": "14.85 0.75 1.25",
        "equ_unbias": {
            "N0": "",
            "N1": "",
            "N2": "",
            "N0 + N1": "",
            "N0 - N1": "",
            "N0 * N1": "",
            "N0 / N1": "",
            "N0 + N2": "",
            "N0 - N2": "",
            "N0 * N2": "",
            "N0 / N2": "",
            "N1 - N0": "",
            "N1 / N0": "",
            "N1 + N2": "",
            "N1 - N2": "",
            "N1 * N2": "",
            "N1 / N2": "",
            "N2 - N0": "",
            "N2 / N0": "",
            "N2 - N1": "",
            "N2 / N1": "",
            "( N0 - N1 ) - N2": "这时电线还剩多少米？",
            "( N0 + N1 ) - N2": "",
            "( N0 - N1 ) + N2": "",
            "( N0 - N1 ) * N2": "",
            "( N0 - N1 ) / N2": "",
            "( N0 * N1 ) - N2": "",
            "( N0 / N1 ) - N2": ""
        }
    },
    {
        "id": "a28040cbbe8c11eb82ae04d4c4250d10",
        "original_text": "一台碾米机每小时可碾米0.8吨,4台同样的碾米机8.5小时可碾米多少吨?",
        "mask_text": "一台 碾米机 每 小时 可 碾米 N0 吨 , N1 台 同样 的 碾米机 N2 小时 可 碾米 多少 吨 ?",
        "context": "一台碾米机每小时可碾米0.8吨,4台同样的碾米机8.",
        "original_question": "5小时可碾米多少吨?",
        "nums": "0.8 4 8.5",
        "equ_unbias": {
            "N0": "",
            "N1": "",
            "N2": "",
            "N0 + N1": "",
            "N0 - N1": "",
            "N0 * N1": "",
            "N0 / N1": "",
            "N0 + N2": "",
            "N0 - N2": "",
            "N0 * N2": "",
            "N0 / N2": "",
            "N1 - N0": "",
            "N1 / N0": "",
            "N1 + N2": "",
            "N1 - N2": "",
            "N1 * N2": "",
            "N1 / N2": "",
            "N2 - N0": "",
            "N2 / N0": "",
            "N2 - N1": "",
            "N2 / N1": "",
            "( N0 * N1 ) * N2": "5小时可碾米多少吨?"
        }
    },
    {
        "id": "a65a430ebe8c11ebb85104d4c4250d10",
        "original_text": "食堂运进一批煤，计划每天烧0.3吨，可以烧20天，如果每天烧0.25吨，能烧多少天？",
        "mask_text": "食堂 运进 一批 煤 ， 计划 每天 烧 N0 吨 ， 可以 烧 N1 天 ， 如果 每天 烧 N2 吨 ， 能烧 多少 天 ？",
        "context": "食堂运进一批煤，计划每天烧0.3吨，可以烧20天，如果每天烧0.25吨，",
        "original_question": "能烧多少天？",
        "nums": "0.3 20 0.25",
        "equ_unbias": {
            "N0": "",
            "N1": "",
            "N2": "",
            "N0 + N1": "",
            "N0 - N1": "",
            "N0 * N1": "",
            "N0 / N1": "",
            "N0 + N2": "",
            "N0 - N2": "",
            "N0 * N2": "",
            "N0 / N2": "",
            "N1 - N0": "",
            "N1 / N0": "",
            "N1 + N2": "",
            "N1 - N2": "",
            "N1 * N2": "",
            "N1 / N2": "",
            "N2 - N0": "",
            "N2 / N0": "",
            "N2 - N1": "",
            "N2 / N1": "",
            "( N0 * N1 ) / N2": "能烧多少天？",
            "( N0 + N1 ) / N2": "",
            "( N0 * N1 ) + N2": "",
            "( N0 * N1 ) - N2": "",
            "( N0 * N1 ) * N2": "",
            "( N0 - N1 ) / N2": "",
            "( N0 / N1 ) / N2": ""
        }
    },
    {
        "id": "a4f49de1be8c11eb8ea404d4c4250d10",
        "original_text": "一个玩具厂原来生产某种玩具的成本是每个4.5元，改进制造工艺后每个玩具成本只要3.6元。原来生产400个玩具的成本，现在可以生产多少个玩具？",
        "mask_text": "一个 玩具厂 原来 生产 某种 玩具 的 成本 是 每个 N0 元 ， 改进 制造 工艺 后 每个 玩具 成本 只要 N1 元 。 原来 生产 N2 个 玩具 的 成本 ， 现在 可以 生产 多少 个 玩具 ？",
        "context": "一个玩具厂原来生产某种玩具的成本是每个4.5元，改进制造工艺后每个玩具成本只要3.6元。原来生产400个玩具的成本，",
        "original_question": "现在可以生产多少个玩具？",
        "nums": "4.5 3.6 400",
        "equ_unbias": {
            "N2": "",
            "N0": "",
            "N1": "",
            "N2 + N0": "",
            "N2 - N0": "",
            "N2 * N0": "",
            "N2 / N0": "",
            "N2 + N1": "",
            "N2 - N1": "",
            "N2 * N1": "",
            "N2 / N1": "",
            "N0 - N2": "",
            "N0 / N2": "",
            "N0 + N1": "",
            "N0 - N1": "",
            "N0 * N1": "",
            "N0 / N1": "",
            "N1 - N2": "",
            "N1 / N2": "",
            "N1 - N0": "",
            "N1 / N0": "",
            "( N2 * N0 ) / N1": "现在可以生产多少个玩具？",
            "( N2 + N0 ) / N1": "",
            "( N2 * N0 ) + N1": "",
            "( N2 * N0 ) - N1": "",
            "( N2 * N0 ) * N1": "",
            "( N2 - N0 ) / N1": "",
            "( N2 / N0 ) / N1": ""
        }
    },
    {
        "id": "a9a117cebe8c11eb8ec204d4c4250d10",
        "original_text": "某煤场运煤，第一次运进260吨，第二次运进356吨，第三次运进的和第一次同样多，三次一共运进多少吨？",
        "mask_text": "某 煤场 运煤 ， 第一次 运进 N0 吨 ， 第二次 运进 N1 吨 ， 第三次 运进 的 和 第一次 同样 多 ， 三次 一共 运进 多少 吨 ？",
        "context": "某煤场运煤，第一次运进260吨，第二次运进356吨，第三次运进的和第一次同样多，",
        "original_question": "三次一共运进多少吨？",
        "nums": "260 356",
        "equ_unbias": {
            "N0": "",
            "N1": "",
            "N0 + N1": "",
            "N0 - N1": "",
            "N0 * N1": "",
            "N0 / N1": "",
            "N0 + N0": "",
            "N0 - N0": "",
            "N0 * N0": "",
            "N0 / N0": "",
            "N1 - N0": "",
            "N1 / N0": "",
            "N1 + N0": "",
            "N1 * N0": "",
            "( N0 + N1 ) + N0": "三次一共运进多少吨？",
            "( N0 + N1 ) - N0": "",
            "( N0 + N1 ) * N0": "",
            "( N0 + N1 ) / N0": "",
            "( N0 - N1 ) + N0": "",
            "( N0 * N1 ) + N0": "",
            "( N0 / N1 ) + N0": ""
        }
    },
    {
        "id": "a30f771fbe8c11ebbfff04d4c4250d10",
        "original_text": "甲地到乙地的距离是80千米，乙地到丙地的距离比甲地到乙地的距离的3倍少20千米。一辆汽车从乙地到丙地行驶了4小时，这辆汽车平均每小时行驶多少千米？",
        "mask_text": "甲地 到 乙地 的 距离 是 N0 千米 ， 乙地 到 丙地 的 距离 比 甲地 到 乙地 的 距离 的 N1 倍少 N2 千米 。 一辆 汽车 从 乙地 到 丙地 行驶 了 N3 小时 ， 这辆 汽车 平均 每 小时 行驶 多少 千米 ？",
        "context": "甲地到乙地的距离是80千米，乙地到丙地的距离比甲地到乙地的距离的3倍少20千米。一辆汽车从乙地到丙地行驶了4小时，",
        "original_question": "这辆汽车平均每小时行驶多少千米？",
        "nums": "80 3 20 4",
        "equ_unbias": {
            "N0": "",
            "N1": "",
            "N2": "",
            "N3": "",
            "N0 + N1": "",
            "N0 - N1": "",
            "N0 * N1": "",
            "N0 / N1": "",
            "N0 + N2": "",
            "N0 - N2": "",
            "N0 * N2": "",
            "N0 / N2": "",
            "N0 + N3": "",
            "N0 - N3": "",
            "N0 * N3": "",
            "N0 / N3": "",
            "N1 - N0": "",
            "N1 / N0": "",
            "N1 + N2": "",
            "N1 - N2": "",
            "N1 * N2": "",
            "N1 / N2": "",
            "N1 + N3": "",
            "N1 - N3": "",
            "N1 * N3": "",
            "N1 / N3": "",
            "N2 - N0": "",
            "N2 / N0": "",
            "N2 - N1": "",
            "N2 / N1": "",
            "N2 + N3": "",
            "N2 - N3": "",
            "N2 * N3": "",
            "N2 / N3": "",
            "N3 - N0": "",
            "N3 / N0": "",
            "N3 - N1": "",
            "N3 / N1": "",
            "N3 - N2": "",
            "N3 / N2": "",
            "( N0 * N1 ) - N2": "",
            "( ( N0 * N1 ) - N2 ) / N3": "这辆汽车平均每小时行驶多少千米？",
            "( N0 + N1 ) - N2": "",
            "( N0 * N1 ) + N2": "",
            "( N0 * N1 ) * N2": "",
            "( N0 * N1 ) / N2": "",
            "( N0 - N1 ) - N2": "",
            "( N0 / N1 ) - N2": ""
        }
    },
    {
        "id": "a432bcebbe8c11ebbb1104d4c4250d10",
        "original_text": "台电暖气128元，1台热水器比它贵426元，买1台电暖气和1台电热水器一共要多少钱？",
        "mask_text": "台 电暖气 N0 元 ， N1 台 热水器 比 它 贵 N2 元 ， 买 N3 台 电暖气 和 N4 台 电热水器 一共 要 多少 钱 ？",
        "context": "台电暖气128元，1台热水器比它贵426元，",
        "original_question": "买1台电暖气和1台电热水器一共要多少钱？",
        "nums": "128 1 426 1 1",
        "equ_unbias": {
            "N0": "",
            "N3": "",
            "N2": "",
            "N4": "",
            "N0 + N3": "",
            "N0 - N3": "",
            "N0 * N3": "",
            "N0 / N3": "",
            "N0 + N0": "",
            "N0 - N0": "",
            "N0 * N0": "",
            "N0 / N0": "",
            "N0 + N2": "",
            "N0 - N2": "",
            "N0 * N2": "",
            "N0 / N2": "",
            "N0 + N4": "",
            "N0 - N4": "",
            "N0 * N4": "",
            "N0 / N4": "",
            "N3 - N0": "",
            "N3 / N0": "",
            "N3 + N0": "",
            "N3 * N0": "",
            "N3 + N2": "",
            "N3 - N2": "",
            "N3 * N2": "",
            "N3 / N2": "",
            "N3 + N4": "",
            "N3 - N4": "",
            "N3 * N4": "",
            "N3 / N4": "",
            "N2 - N0": "",
            "N2 / N0": "",
            "N2 - N3": "",
            "N2 / N3": "",
            "N2 + N4": "",
            "N2 - N4": "",
            "N2 * N4": "",
            "N2 / N4": "",
            "N4 - N0": "",
            "N4 / N0": "",
            "N4 - N3": "",
            "N4 / N3": "",
            "N4 - N2": "",
            "N4 / N2": "",
            "( N0 * N3 ) + ( ( N0 + N2 ) * N4 )": "买1台电暖气和1台电热水器一共要多少钱？"
        }
    },
    {
        "id": "a19f0796be8c11ebaa4404d4c4250d10",
        "original_text": "王老师从家骑车到学校要用0.25小时，每小时行驶18千米，家离学校有多远？",
        "mask_text": "王老师 从家 骑车到 学校 要用 N0 小时 ， 每 小时 行驶 N1 千米 ， 家离 学校 有多远 ？",
        "context": "王老师从家骑车到学校要用0.25小时，每小时行驶18千米，",
        "original_question": "家离学校有多远？",
        "nums": "0.25 18",
        "equ_unbias": {
            "N0": "",
            "N1": "",
            "N0 + N1": "",
            "N0 - N1": "",
            "N0 * N1": "家离学校有多远？",
            "N0 / N1": "",
            "N1 - N0": "",
            "N1 / N0": ""
        }
    },
    {
        "id": "a9c68679be8c11eba00f04d4c4250d10",
        "original_text": "斑马和小鸡一共有43只，其中斑马有18只．斑马比小鸡少几只？",
        "mask_text": "斑马 和 小鸡 一共 有 N0 只 ， 其中 斑马 有 N1 只 ． 斑马 比 小鸡 少 几只 ？",
        "context": "斑马和小鸡一共有43只，其中斑马有18只．",
        "original_question": "斑马比小鸡少几只？",
        "nums": "43 18",
        "equ_unbias": {
            "N0": "",
            "N1": "",
            "N0 + N1": "",
            "N0 - N1": "",
            "N0 * N1": "",
            "N0 / N1": "",
            "N1 - N0": "",
            "N1 / N0": "",
            "N1 + N1": "",
            "N1 - N1": "",
            "N1 * N1": "",
            "N1 / N1": "",
            "( N0 - N1 ) - N1": "斑马比小鸡少几只？",
            "( N0 + N1 ) - N1": "",
            "( N0 - N1 ) + N1": "",
            "( N0 - N1 ) * N1": "",
            "( N0 - N1 ) / N1": "",
            "( N0 * N1 ) - N1": "",
            "( N0 / N1 ) - N1": ""
        }
    },
    {
        "id": "a261d133be8c11eb87a804d4c4250d10",
        "original_text": "水果店运进苹果504千克，梨299克，运进的苹果比梨大约多多少千克？",
        "mask_text": "水果店 运进 苹果 N0 千克 ， 梨 N1 克 ， 运进 的 苹果 比梨 大约 多 多少 千克 ？",
        "context": "水果店运进苹果504千克，梨299克，",
        "original_question": "运进的苹果比梨大约多多少千克？",
        "nums": "504 299",
        "equ_unbias": {
            "N0": "",
            "N1": "",
            "N0 + N1": "",
            "N0 - N1": "运进的苹果比梨大约多多少千克？",
            "N0 * N1": "",
            "N0 / N1": "",
            "N1 - N0": "",
            "N1 / N0": ""
        }
    }
]